filenames-secure/__init__.py
filenames_secure/__init__.py
filenames_secure-0.0.7.dist-info/METADATA
filenames_secure-0.0.7.dist-info/WHEEL
filenames_secure-0.0.7.dist-info/entry_points.txt
filenames_secure-0.0.7.dist-info/top_level.txt
filenames_secure-0.0.7.dist-info/RECORD
