Metadata-Version: 2.1
Name: filenames-secure
Version: 0.0.7
Summary: Obscure filenames of mp4 files - away from being embarrassed by accidently opening family videos at work!
Home-page: https://gitee.com/yanhuihang/filenames_secure
Author: YAN Hui Hang, GDUFS
Author-email: yanhuihang@126.com
License: UNKNOWN
Platform: UNKNOWN
Classifier: Programming Language :: Python :: 3
Classifier: Operating System :: OS Independent
Requires-Python: >=3.6
